MANIFEST.in
README.rst
setup.cfg
setup.py
examples/99-icsectl.rules
examples/icsectl
examples/icseudev
icsectl/__init__.py
icsectl.egg-info/PKG-INFO
icsectl.egg-info/SOURCES.txt
icsectl.egg-info/dependency_links.txt
icsectl.egg-info/top_level.txt