Metadata-Version: 1.1
Name: icsectl
Version: 0.2
Summary: Control the ICStation USB multi channel relay modules
Home-page: https://github.com/xypron/pysispm
Author: Heinrich Schuchardt
Author-email: xypron.glpk@gmx.de
License: BSD
Platform: UNKNOWN
Classifier: Development Status :: 4 - Beta
Classifier: Intended Audience :: Developers
Classifier: License :: OSI Approved :: BSD License
Classifier: Operating System :: POSIX
Classifier: Programming Language :: Python :: 3
Classifier: Topic :: System :: Hardware :: Hardware Drivers
